{
  "version": "5",
  "dialect": "sqlite",
  "id": "b0b763a0-4484-4f49-bd34-5186cae852f1",
  "prevId": "00000000-0000-0000-0000-000000000000",
  "tables": {
    "User": {
      "name": "User",
      "columns": {
        "id": {
          "name": "id",
          "type": "text",
          "primaryKey": true,
          "notNull": true
        }
      },
      "indexes": {},
      "foreignKeys": {},
      "compositePrimaryKeys": {}
    }
  },
  "enums": {},
  "_meta": {
    "schemas": {},
    "tables": {},
    "columns": {}
  }
}